infobip_cpaasx/__init__.py
infobip_cpaasx/api_client.py
infobip_cpaasx/configuration.py
infobip_cpaasx/exceptions.py
infobip_cpaasx/rest.py
infobip_cpaasx/api/__init__.py
infobip_cpaasx/api/application_api.py
infobip_cpaasx/api/entity_api.py
infobip_cpaasx/api/mms_api.py
infobip_cpaasx/api/number_registration_api.py
infobip_cpaasx/api/numbers_api.py
infobip_cpaasx/api/resource_association_api.py
infobip_cpaasx/api/sms_api.py
infobip_cpaasx/models/__init__.py
infobip_cpaasx/models/application.py
infobip_cpaasx/models/channel.py
infobip_cpaasx/models/entity.py
infobip_cpaasx/models/message_error.py
infobip_cpaasx/models/message_price.py
infobip_cpaasx/models/message_status.py
infobip_cpaasx/models/mms_advanced_message.py
infobip_cpaasx/models/mms_advanced_message_segment.py
infobip_cpaasx/models/mms_advanced_message_segment_binary.py
infobip_cpaasx/models/mms_advanced_message_segment_link.py
infobip_cpaasx/models/mms_advanced_message_segment_smil.py
infobip_cpaasx/models/mms_advanced_message_segment_text.py
infobip_cpaasx/models/mms_advanced_message_segment_upload_reference.py
infobip_cpaasx/models/mms_advanced_request.py
infobip_cpaasx/models/mms_delivery_day.py
infobip_cpaasx/models/mms_delivery_time.py
infobip_cpaasx/models/mms_delivery_time_window.py
infobip_cpaasx/models/mms_destination.py
infobip_cpaasx/models/mms_error.py
infobip_cpaasx/models/mms_inbound_report.py
infobip_cpaasx/models/mms_inbound_report_response.py
infobip_cpaasx/models/mms_message_result.py
infobip_cpaasx/models/mms_price.py
infobip_cpaasx/models/mms_report.py
infobip_cpaasx/models/mms_report_response.py
infobip_cpaasx/models/mms_send_result.py
infobip_cpaasx/models/mms_status.py
infobip_cpaasx/models/mms_upload_binary_result.py
infobip_cpaasx/models/mms_webhook_inbound_message_segment.py
infobip_cpaasx/models/mms_webhook_inbound_message_segment_link.py
infobip_cpaasx/models/mms_webhook_inbound_message_segment_text.py
infobip_cpaasx/models/mms_webhook_inbound_report.py
infobip_cpaasx-0.0.2.dist-info/LICENSE
infobip_cpaasx-0.0.2.dist-info/METADATA
infobip_cpaasx-0.0.2.dist-info/WHEEL
infobip_cpaasx-0.0.2.dist-info/top_level.txt
infobip_cpaasx-0.0.2.dist-info/RECORD
