Metadata-Version: 2.1
Name: infobip-cpaasx
Version: 0.0.2
Summary: Infobip CPaaS X Python Client Library
Home-page: https://github.com/infobip/infobip-cpaasx-python-client
Author: Infobip Ltd.
Author-email: support@infobip.com
License: MIT
Keywords: sms,mms,numbers,cpaas,infobip
Classifier: Intended Audience :: Telecommunications Industry
Classifier: Intended Audience :: Information Technology
Classifier: Intended Audience :: Developers
Classifier: Programming Language :: Python
Classifier: Operating System :: OS Independent
Classifier: Topic :: Software Development :: Libraries :: Python Modules
Classifier: Topic :: Software Development :: Libraries
License-File: LICENSE
Requires-Dist: urllib3 (>=1.25.3)
Requires-Dist: python-dateutil
Requires-Dist: pydantic
Requires-Dist: aenum
